{"cameraMode":{"drawMode":0,"name":"Shaded","section":"Shading Mode"},"sceneLighting":true,"audioPlay":false,"sceneViewState":{"showFog":true,"showMaterialUpdate":false,"showSkybox":true,"showFlares":true,"showImageEffects":true,"showParticleSystems":true},"in2DMode":false,"pivot":{"x":16.568187713623048,"y":6.733974456787109,"z":-0.8432148694992065},"rotation":{"x":0.061548251658678058,"y":-0.7671452164649963,"z":-0.07350635528564453,"w":-0.6345711946487427},"size":9.550000190734864,"orthographic":false}