{"cameraMode":{"drawMode":0,"name":"Shaded","section":"Shading Mode"},"sceneLighting":true,"audioPlay":false,"sceneViewState":{"showFog":true,"showMaterialUpdate":false,"showSkybox":true,"showFlares":true,"showImageEffects":true,"showParticleSystems":true},"in2DMode":false,"pivot":{"x":1.8733810186386109,"y":2.8157076835632326,"z":3.8070127964019777},"rotation":{"x":0.028829876333475114,"y":-0.8365041017532349,"z":0.0442165769636631,"w":0.5454146862030029},"size":0.04750105366110802,"orthographic":false}